demo/__init__.py
demo/test.py
recxdemo-0.1.dist-info/DESCRIPTION.rst
recxdemo-0.1.dist-info/METADATA
recxdemo-0.1.dist-info/RECORD
recxdemo-0.1.dist-info/WHEEL
recxdemo-0.1.dist-info/metadata.json
recxdemo-0.1.dist-info/top_level.txt
