Metadata-Version: 1.0
Name: recxdemo
Version: 0.1
Summary: The funniest demo in the world
Home-page: http://github.com/sleprecx
Author: Markus Andresen
Author-email: flyingcircus@example.com
License: MIT
Platform: UNKNOWN
